FSM Assignment/P3_vending/vending_mealy.v
`timescale 1ns/1ps

module vending_mealy(
    input wire clk,
    input wire rst,          // synchronous active-high reset
    input wire [1:0] coin,   // 01=5, 10=10, 00=idle, 11=invalid
    output reg dispense,     // 1-cycle pulse
    output reg chg5          // 1-cycle pulse when returning 5
);

    // State encoding (total inserted so far)
    localparam S0  = 2'b00;
    localparam S5  = 2'b01;
    localparam S10 = 2'b10;
    localparam S15 = 2'b11;

    reg [1:0] state, next_state;

    // Next-state and output logic (Mealy)
    always @(*) begin
        // defaults
        next_state = state;
        dispense   = 0;
        chg5       = 0;

        case (state)
            S0: begin
                if (coin == 2'b01) next_state = S5;        // +5
                else if (coin == 2'b10) next_state = S10;  // +10
            end

            S5: begin
                if (coin == 2'b01) next_state = S10;       // +5
                else if (coin == 2'b10) next_state = S15;  // +10
            end

            S10: begin
                if (coin == 2'b01) next_state = S15;       // +5
                else if (coin == 2'b10) begin
                    // total = 20 → dispense
                    dispense   = 1;
                    next_state = S0;
                end
            end

            S15: begin
                if (coin == 2'b01) begin
                    // total = 20 → dispense
                    dispense   = 1;
                    next_state = S0;
                end
                else if (coin == 2'b10) begin
                    // total = 25 → dispense + change
                    dispense   = 1;
                    chg5       = 1;
                    next_state = S0;
                end
            end
        endcase
    end

    // State register
    always @(posedge clk) begin
        if (rst) state <= S0;
        else     state <= next_state;
    end

endmodule

FSM Assignment/P3_vending/tb_vending_mealy.v
`timescale 1ns/1ps

module tb_vending_mealy;

    reg clk, rst;
    reg [1:0] coin;
    wire dispense, chg5;

    // DUT instance
    vending_mealy dut(
        .clk(clk),
        .rst(rst),
        .coin(coin),
        .dispense(dispense),
        .chg5(chg5)
    );

    // Clock generation (10ns period = 100MHz)
    initial begin
        clk = 0;
        forever #5 clk = ~clk;
    end

    // Stimulus
    initial begin
        // Dumpfile for GTKWave
        $dumpfile("dump.vcd");
        $dumpvars(0, tb_vending_mealy);

        // Reset
        rst = 1; coin = 2'b00;
        #12 rst = 0;

        // --- Test cases ---
        // Case 1: 10 + 10 = 20 → dispense
        put10();
        put10();

        // Case 2: 5 + 5 + 10 = 20 → dispense
        put5();
        put5();
        put10();

        // Case 3: 10 + 5 + 10 = 25 → dispense + change
        put10();
        put5();
        put10();

        // Finish
        #50 $finish;
    end

    // Tasks to insert coins
    task put5;
        begin
            @(negedge clk);
            coin = 2'b01;
            @(negedge clk);
            coin = 2'b00; // idle
        end
    endtask

    task put10;
        begin
            @(negedge clk);
            coin = 2'b10;
            @(negedge clk);
            coin = 2'b00; // idle
        end
    endtask

endmodule

FSM Assignment/P3_vending/dump.vcd
$date
	Tue Sep 02 11:13:37 2025
$end
$version
	Icarus Verilog
$end
$timescale
	1ps
$end
$scope module tb_vending_mealy $end
$var wire 1 ! dispense $end
$var wire 1 " chg5 $end
$var reg 1 # clk $end
$var reg 2 $ coin [1:0] $end
$var reg 1 % rst $end
$scope module dut $end
$var wire 1 # clk $end
$var wire 2 & coin [1:0] $end
$var wire 1 % rst $end
$var parameter 2 ' S0 $end
$var parameter 2 ( S10 $end
$var parameter 2 ) S15 $end
$var parameter 2 * S5 $end
$var reg 1 " chg5 $end
$var reg 1 ! dispense $end
$var reg 2 + next_state [1:0] $end
$var reg 2 , state [1:0] $end
$upscope $end
$scope task put10 $end
$upscope $end
$scope task put5 $end
$upscope $end
$upscope $end
$enddefinitions $end
$comment Show the parameter values. $end
$dumpall
b1 *
b11 )
b10 (
b0 '
$end
#0
$dumpvars
bx ,
bx +
b0 &
1%
b0 $
0#
0"
0!
$end
#5000
b0 +
b0 ,
1#
#10000
0#
#12000
0%
#15000
1#
#20000
b10 +
b10 $
b10 &
0#
#25000
b0 +
1!
b10 ,
1#
#30000
0!
b10 +
b0 $
b0 &
0#
#35000
1#
#40000
b0 +
1!
b10 $
b10 &
0#
#45000
b10 +
0!
b0 ,
1#
#50000
b0 +
b0 $
b0 &
0#
#55000
1#
#60000
b1 +
b1 $
b1 &
0#
#65000
b10 +
b1 ,
1#
#70000
b1 +
b0 $
b0 &
0#
#75000
1#
#80000
b10 +
b1 $
b1 &
0#
#85000
b11 +
b10 ,
1#
#90000
b10 +
b0 $
b0 &
0#
#95000
1#
#100000
b0 +
1!
b10 $
b10 &
0#
#105000
b10 +
0!
b0 ,
1#
#110000
b0 +
b0 $
b0 &
0#
#115000
1#
#120000
b10 +
b10 $
b10 &
0#
#125000
b0 +
1!
b10 ,
1#
#130000
0!
b10 +
b0 $
b0 &
0#
#135000
1#
#140000
b11 +
b1 $
b1 &
0#
#145000
b0 +
1!
b11 ,
1#
#150000
0!
b11 +
b0 $
b0 &
0#
#155000
1#
#160000
b0 +
1"
1!
b10 $
b10 &
0#
#165000
b10 +
0"
0!
b0 ,
1#
#170000
b0 +
b0 $
b0 &
0#
