FSM Assignment/P4_link/slave_fsm.v
// slave_fsm.v — latches data, asserts ack for >=2 cycles, drops after req falls
module slave_fsm(
  input  wire       clk,
  input  wire       rst,
  input  wire       req,
  input  wire [7:0] data_in,
  output reg        ack,
  output reg [7:0]  last_byte
);

  // states
  parameter W_WAIT_REQ = 2'd0,
            W_ASSERT   = 2'd1,
            W_HOLD     = 2'd2,
            W_DROP     = 2'd3;

  reg [1:0] state, nstate;
  reg [1:0] hold_cnt;

  // sequential
  always @(posedge clk) begin
    if (rst) begin
      state     <= W_WAIT_REQ;
      hold_cnt  <= 2'd0;
      ack       <= 1'b0;
      last_byte <= 8'h00;
    end else begin
      state <= nstate;

      case (state)
        W_WAIT_REQ: begin
          ack <= 1'b0;
          if (req) begin
            last_byte <= data_in;
            ack       <= 1'b1;
            hold_cnt  <= 2'd0;
          end
        end
        W_ASSERT: begin
          ack <= 1'b1;
          hold_cnt <= hold_cnt + 1;
        end
        W_HOLD: begin
          ack <= 1'b1;
        end
        W_DROP: begin
          ack <= 1'b0;
        end
      endcase
    end
  end

  // next-state
  always @(*) begin
    nstate = state;
    case (state)
      W_WAIT_REQ: if (req) nstate = W_ASSERT;
      W_ASSERT:   if (hold_cnt == 2'd1) nstate = (req ? W_HOLD : W_DROP);
      W_HOLD:     if (!req) nstate = W_DROP;
      W_DROP:     nstate = W_WAIT_REQ;
    endcase
  end

endmodule

FSM Assignment/P4_link/master_fsm.v
// master_fsm.v — 4-byte burst master with 4-phase req/ack
module master_fsm(
  input  wire       clk,
  input  wire       rst,     // synchronous, active-high
  input  wire       ack,
  output reg        req,
  output reg [7:0]  data,
  output reg        done     // 1-cycle pulse after 4th transfer
);

  // state encoding
  parameter S_IDLE       = 3'd0,
            S_DRIVE      = 3'd1,
            S_WAIT_ACK   = 3'd2,
            S_DROP_REQ   = 3'd3,
            S_WAIT_ACK0  = 3'd4,
            S_DONE_PULSE = 3'd5;

  reg [2:0] state, nstate;
  reg [1:0] idx;         // 0..3 (four bytes)
  reg [7:0] rom [0:3];

  // simple pattern A0..A3
  initial begin
    rom[0] = 8'hA0;
    rom[1] = 8'hA1;
    rom[2] = 8'hA2;
    rom[3] = 8'hA3;
  end

  // sequential
  always @(posedge clk) begin
    if (rst) begin
      state <= S_IDLE;
      idx   <= 2'd0;
      data  <= 8'h00;
      req   <= 1'b0;
      done  <= 1'b0;
    end else begin
      state <= nstate;
      if (nstate != S_DONE_PULSE) done <= 1'b0;

      case (state)
        S_IDLE: begin
          req <= 1'b0;
        end
        S_DRIVE: begin
          data <= rom[idx];
          req  <= 1'b1;
        end
        S_WAIT_ACK: begin
          req  <= 1'b1;
        end
        S_DROP_REQ: begin
          req  <= 1'b0;
        end
        S_WAIT_ACK0: begin
          req  <= 1'b0;
        end
        S_DONE_PULSE: begin
          done <= 1'b1;
          req  <= 1'b0;
        end
      endcase
    end
  end

  // next-state
  always @(*) begin
    nstate = state;
    case (state)
      S_IDLE:       nstate = S_DRIVE;
      S_DRIVE:      nstate = S_WAIT_ACK;
      S_WAIT_ACK:   if (ack) nstate = S_DROP_REQ;
      S_DROP_REQ:   nstate = S_WAIT_ACK0;
      S_WAIT_ACK0:  if (!ack)
                      if (idx == 2'd3) nstate = S_DONE_PULSE;
                      else             nstate = S_DRIVE;
      S_DONE_PULSE: nstate = S_IDLE;
    endcase
  end

  // index update
  always @(posedge clk) begin
    if (rst) begin
      idx <= 2'd0;
    end else if (state == S_WAIT_ACK0 && !ack) begin
      if (idx == 2'd3) idx <= 2'd0;
      else             idx <= idx + 2'd1;
    end
  end

endmodule

FSM Assignment/P4_link/link_top.v
module link_top(
  input  wire clk,
  input  wire rst,
  output wire done
);
  wire        req, ack;
  wire [7:0]  data_bus;
  wire [7:0]  last_byte;

  master_fsm u_master(
    .clk(clk), .rst(rst),
    .ack(ack),
    .req(req),
    .data(data_bus),
    .done(done)
  );

  slave_fsm u_slave(
    .clk(clk), .rst(rst),
    .req(req),
    .data_in(data_bus),
    .ack(ack),
    .last_byte(last_byte)
  );
endmodule

FSM Assignment/P4_link/tb_link_top.v
`timescale 1ns/1ps
module tb_link_top;

  reg clk = 0;
  reg rst = 1;
  wire done;

  link_top dut(.clk(clk), .rst(rst), .done(done));

  always #5 clk = ~clk; // 100 MHz

  initial begin
    $dumpfile("dump.vcd");
    $dumpvars(0, tb_link_top);

    repeat (4) @(posedge clk);
    rst <= 0;

    wait (done == 1'b1);
    @(posedge clk);
    repeat (5) @(posedge clk);

    $display("DONE observed at %0t", $time);
    $finish;
  end

  wire req   = dut.u_master.req;
  wire ack   = dut.u_slave.ack;
  wire [7:0] data = dut.u_master.data;
  wire [7:0] last = dut.u_slave.last_byte;

  always @(posedge clk) begin
    if (!rst)
      $strobe("t=%0t req=%b ack=%b data=%h last=%h done=%b",
              $time, req, ack, data, last, done);
  end
endmodule

FSM Assignment/P4_link/dump.vcd
$date
	Tue Sep 02 09:04:43 2025
$end
$version
	Icarus Verilog
$end
$timescale
	1ps
$end
$scope module tb_link_top $end
$var wire 1 ! ack $end
$var wire 8 " data [7:0] $end
$var wire 8 # last [7:0] $end
$var wire 1 $ req $end
$var wire 1 % done $end
$var reg 1 & clk $end
$var reg 1 ' rst $end
$scope module dut $end
$var wire 1 & clk $end
$var wire 1 ' rst $end
$var wire 1 ( req $end
$var wire 8 ) last_byte [7:0] $end
$var wire 1 % done $end
$var wire 8 * data_bus [7:0] $end
$var wire 1 + ack $end
$scope module u_master $end
$var wire 1 & clk $end
$var wire 1 ' rst $end
$var wire 1 + ack $end
$var parameter 3 , S_DONE_PULSE $end
$var parameter 3 - S_DRIVE $end
$var parameter 3 . S_DROP_REQ $end
$var parameter 3 / S_IDLE $end
$var parameter 3 0 S_WAIT_ACK $end
$var parameter 3 1 S_WAIT_ACK0 $end
$var reg 8 2 data [7:0] $end
$var reg 1 % done $end
$var reg 2 3 idx [1:0] $end
$var reg 3 4 nstate [2:0] $end
$var reg 1 ( req $end
$var reg 3 5 state [2:0] $end
$upscope $end
$scope module u_slave $end
$var wire 1 & clk $end
$var wire 8 6 data_in [7:0] $end
$var wire 1 ( req $end
$var wire 1 ' rst $end
$var parameter 2 7 W_ASSERT $end
$var parameter 2 8 W_DROP $end
$var parameter 2 9 W_HOLD $end
$var parameter 2 : W_WAIT_REQ $end
$var reg 1 + ack $end
$var reg 2 ; hold_cnt [1:0] $end
$var reg 8 < last_byte [7:0] $end
$var reg 2 = nstate [1:0] $end
$var reg 2 > state [1:0] $end
$upscope $end
$upscope $end
$upscope $end
$enddefinitions $end
$comment Show the parameter values. $end
$dumpall
b0 :
b10 9
b11 8
b1 7
b100 1
b10 0
b0 /
b11 .
b1 -
b101 ,
$end
#0
$dumpvars
bx >
bx =
bx <
bx ;
bx 6
bx 5
bx 4
bx 3
bx 2
x+
bx *
bx )
x(
1'
0&
x%
x$
bx #
bx "
x!
$end
#5000
b1 4
b0 =
0%
0$
0(
b0 "
b0 *
b0 2
b0 6
b0 5
b0 3
b0 #
b0 )
b0 <
0!
0+
b0 ;
b0 >
1&
#10000
0&
#15000
1&
#20000
0&
#25000
1&
#30000
0&
#35000
0'
1&
#40000
0&
#45000
b10 4
b1 5
1&
#50000
0&
#55000
b1 =
1$
1(
b10100000 "
b10100000 *
b10100000 2
b10100000 6
b10 5
1&
#60000
0&
#65000
b11 4
1!
1+
b10100000 #
b10100000 )
b10100000 <
b1 >
1&
#70000
0&
#75000
b10 =
b100 4
b1 ;
b11 5
1&
#80000
0&
#85000
b11 =
0$
0(
b100 5
b10 ;
b10 >
1&
#90000
0&
#95000
b0 =
b11 >
1&
#100000
0&
#105000
b1 4
0!
0+
b0 >
1&
#110000
0&
#115000
b10 4
b1 3
b1 5
1&
#120000
0&
#125000
b1 =
1$
1(
b10100001 "
b10100001 *
b10100001 2
b10100001 6
b10 5
1&
#130000
0&
#135000
b11 4
b0 ;
1!
1+
b10100001 #
b10100001 )
b10100001 <
b1 >
1&
#140000
0&
#145000
b100 4
b10 =
b11 5
b1 ;
1&
#150000
0&
#155000
b11 =
b10 ;
b10 >
0$
0(
b100 5
1&
#160000
0&
#165000
b0 =
b11 >
1&
#170000
0&
#175000
b1 4
0!
0+
b0 >
1&
#180000
0&
#185000
b10 4
b1 5
b10 3
1&
#190000
0&
#195000
b1 =
1$
1(
b10100010 "
b10100010 *
b10100010 2
b10100010 6
b10 5
1&
#200000
0&
#205000
b11 4
b0 ;
1!
1+
b10100010 #
b10100010 )
b10100010 <
b1 >
1&
#210000
0&
#215000
b10 =
b100 4
b1 ;
b11 5
1&
#220000
0&
#225000
b11 =
0$
0(
b100 5
b10 ;
b10 >
1&
#230000
0&
#235000
b0 =
b11 >
1&
#240000
0&
#245000
b1 4
0!
0+
b0 >
1&
#250000
0&
#255000
b10 4
b11 3
b1 5
1&
#260000
0&
#265000
b1 =
1$
1(
b10100011 "
b10100011 *
b10100011 2
b10100011 6
b10 5
1&
#270000
0&
#275000
b11 4
b0 ;
1!
1+
b10100011 #
b10100011 )
b10100011 <
b1 >
1&
#280000
0&
#285000
b100 4
b10 =
b11 5
b1 ;
1&
#290000
0&
#295000
b11 =
b10 ;
b10 >
0$
0(
b100 5
1&
#300000
0&
#305000
b0 =
b11 >
1&
#310000
0&
#315000
b101 4
0!
0+
b0 >
1&
#320000
0&
#325000
b0 4
b101 5
b0 3
1&
#330000
0&
#335000
b1 4
1%
b0 5
1&
#340000
0&
#345000
b10 4
0%
b1 5
1&
#350000
0&
#355000
b1 =
1$
1(
b10100000 "
b10100000 *
b10100000 2
b10100000 6
b10 5
1&
#360000
0&
#365000
b11 4
b0 ;
1!
1+
b10100000 #
b10100000 )
b10100000 <
b1 >
1&
#370000
0&
#375000
b10 =
b100 4
b1 ;
b11 5
1&
#380000
0&
#385000
b11 =
0$
0(
b100 5
b10 ;
b10 >
1&
#390000
0&
#395000
b0 =
b11 >
1&
