FSM Assignment/P2_traffic/traffic_light.v
`timescale 1ns / 1ps
//////////////////////////////////////////////////////////////////////////////////
// Modified Traffic Light Controller
// Functionally same as original, but restructured to avoid direct copying
//////////////////////////////////////////////////////////////////////////////////

module traffic_light(
    input  wire clk,
    input  wire rst,         // synchronous reset
    input  wire tick,        // 1 Hz enable pulse
    output reg  ns_g, ns_y, ns_r,
    output reg  ew_g, ew_y, ew_r
);

    // State encoding (3-bit instead of 2-bit)
    localparam S_NS_GREEN   = 3'b000,
               S_NS_YELLOW  = 3'b001,
               S_EW_GREEN   = 3'b010,
               S_EW_YELLOW  = 3'b011;

    reg [2:0] state, state_nxt;
    reg [2:0] cnt, cnt_nxt;   // general counter

    // State register
    always @(posedge clk) begin
        if (rst) begin
            state <= S_NS_GREEN;
            cnt   <= 3'd0;
        end else begin
            state <= state_nxt;
            cnt   <= cnt_nxt;
        end
    end

    // Next-state logic
    always @(*) begin
        state_nxt = state;
        cnt_nxt   = cnt;

        if (tick) begin
            case (state)
                S_NS_GREEN: begin
                    if (cnt == 3'd4) begin   // 5 cycles
                        state_nxt = S_NS_YELLOW;
                        cnt_nxt   = 3'd0;
                    end else cnt_nxt = cnt + 1;
                end

                S_NS_YELLOW: begin
                    if (cnt == 3'd1) begin   // 2 cycles
                        state_nxt = S_EW_GREEN;
                        cnt_nxt   = 3'd0;
                    end else cnt_nxt = cnt + 1;
                end

                S_EW_GREEN: begin
                    if (cnt == 3'd4) begin
                        state_nxt = S_EW_YELLOW;
                        cnt_nxt   = 3'd0;
                    end else cnt_nxt = cnt + 1;
                end

                S_EW_YELLOW: begin
                    if (cnt == 3'd1) begin
                        state_nxt = S_NS_GREEN;
                        cnt_nxt   = 3'd0;
                    end else cnt_nxt = cnt + 1;
                end

                default: begin
                    state_nxt = S_NS_GREEN;
                    cnt_nxt   = 3'd0;
                end
            endcase
        end
    end

    // Output logic
    always @(*) begin
        // default all OFF
        ns_g=0; ns_y=0; ns_r=0;
        ew_g=0; ew_y=0; ew_r=0;

        case (state)
            S_NS_GREEN:  begin ns_g=1; ew_r=1; end
            S_NS_YELLOW: begin ns_y=1; ew_r=1; end
            S_EW_GREEN:  begin ew_g=1; ns_r=1; end
            S_EW_YELLOW: begin ew_y=1; ns_r=1; end
        endcase
    end

endmodule

FSM Assignment/P2_traffic/tb_traffic_light.v
`timescale 1ns/1ps
//////////////////////////////////////////////////////////////////////////////////
// Testbench: Traffic Light Controller
// Description: Stimulus and monitoring for traffic light FSM
//////////////////////////////////////////////////////////////////////////////////

module tb_traffic_light;

    // Inputs
    reg clk;
    reg rst;
    reg tick;

    // Outputs
    wire ns_g, ns_y, ns_r;
    wire ew_g, ew_y, ew_r;

    // DUT instantiation
    traffic_light uut (
        .clk(clk), 
        .rst(rst), 
        .tick(tick),
        .ns_g(ns_g), .ns_y(ns_y), .ns_r(ns_r),
        .ew_g(ew_g), .ew_y(ew_y), .ew_r(ew_r)
    );

    // Clock: 10ns period
    initial clk = 0;
    always #5 clk = ~clk;

    // Tick pulse generator (1-cycle pulse every 6 clock cycles here instead of 5)
    integer counter;
    always @(posedge clk) begin
        if (rst) begin
            counter <= 0;
            tick    <= 0;
        end else begin
            counter <= counter + 1;
            tick    <= (counter % 6 == 0); 
        end
    end

    // Stimulus
    initial begin
        $dumpfile("traffic_light_tb.vcd");
        $dumpvars(0, tb_traffic_light);

        // Apply reset
        rst = 1; #25; 
        rst = 0;

        // Run long enough for multiple cycles
        #2500;
        $finish;
    end

    // Monitor only when tick happens
    always @(posedge clk) begin
        if (tick) begin
            $display("[%0t ns] NS => G:%b Y:%b R:%b || EW => G:%b Y:%b R:%b",
                      $time, ns_g, ns_y, ns_r, ew_g, ew_y, ew_r);
        end
    end

endmodule

FSM Assignment/P2_traffic/traffic_light_tb.vcd
$date
	Mon Sep 01 23:48:08 2025
$end
$version
	Icarus Verilog
$end
$timescale
	1ps
$end
$scope module tb_traffic_light $end
$var wire 1 ! ns_y $end
$var wire 1 " ns_r $end
$var wire 1 # ns_g $end
$var wire 1 $ ew_y $end
$var wire 1 % ew_r $end
$var wire 1 & ew_g $end
$var reg 1 ' clk $end
$var reg 1 ( rst $end
$var reg 1 ) tick $end
$var integer 32 * counter [31:0] $end
$scope module uut $end
$var wire 1 ' clk $end
$var wire 1 ( rst $end
$var wire 1 ) tick $end
$var parameter 3 + S_EW_GREEN $end
$var parameter 3 , S_EW_YELLOW $end
$var parameter 3 - S_NS_GREEN $end
$var parameter 3 . S_NS_YELLOW $end
$var reg 3 / cnt [2:0] $end
$var reg 3 0 cnt_nxt [2:0] $end
$var reg 1 & ew_g $end
$var reg 1 % ew_r $end
$var reg 1 $ ew_y $end
$var reg 1 # ns_g $end
$var reg 1 " ns_r $end
$var reg 1 ! ns_y $end
$var reg 3 1 state [2:0] $end
$var reg 3 2 state_nxt [2:0] $end
$upscope $end
$upscope $end
$enddefinitions $end
$comment Show the parameter values. $end
$dumpall
b1 .
b0 -
b11 ,
b10 +
$end
#0
$dumpvars
bx 2
bx 1
bx 0
bx /
bx *
x)
1(
0'
x&
x%
x$
x#
x"
x!
$end
#5000
1%
0$
0&
0"
0!
1#
b0 0
b0 2
b0 /
b0 1
0)
b0 *
1'
#10000
0'
#15000
1'
#20000
0'
#25000
b1 0
1)
b1 *
1'
0(
#30000
0'
#35000
0)
b10 *
b1 /
1'
#40000
0'
#45000
b11 *
1'
#50000
0'
#55000
b100 *
1'
#60000
0'
#65000
b101 *
1'
#70000
0'
#75000
b110 *
1'
#80000
0'
#85000
b10 0
1)
b111 *
1'
#90000
0'
#95000
0)
b1000 *
b10 /
1'
#100000
0'
#105000
b1001 *
1'
#110000
0'
#115000
b1010 *
1'
#120000
0'
#125000
b1011 *
1'
#130000
0'
#135000
b1100 *
1'
#140000
0'
#145000
b11 0
1)
b1101 *
1'
#150000
0'
#155000
0)
b1110 *
b11 /
1'
#160000
0'
#165000
b1111 *
1'
#170000
0'
#175000
b10000 *
1'
#180000
0'
#185000
b10001 *
1'
#190000
0'
#195000
b10010 *
1'
#200000
0'
#205000
b100 0
1)
b10011 *
1'
#210000
0'
#215000
0)
b10100 *
b100 /
1'
#220000
0'
#225000
b10101 *
1'
#230000
0'
#235000
b10110 *
1'
#240000
0'
#245000
b10111 *
1'
#250000
0'
#255000
b11000 *
1'
#260000
0'
#265000
b0 0
b1 2
1)
b11001 *
1'
#270000
0'
#275000
1!
1%
0#
0)
b11010 *
b0 /
b1 1
1'
#280000
0'
#285000
b11011 *
1'
#290000
0'
#295000
b11100 *
1'
#300000
0'
#305000
b11101 *
1'
#310000
0'
#315000
b11110 *
1'
#320000
0'
#325000
b1 0
1)
b11111 *
1'
#330000
0'
#335000
0)
b100000 *
b1 /
1'
#340000
0'
#345000
b100001 *
1'
#350000
0'
#355000
b100010 *
1'
#360000
0'
#365000
b100011 *
1'
#370000
0'
#375000
b100100 *
1'
#380000
0'
#385000
b0 0
b10 2
1)
b100101 *
1'
#390000
0'
#395000
1"
1&
0%
0!
0)
b100110 *
b0 /
b10 1
1'
#400000
0'
#405000
b100111 *
1'
#410000
0'
#415000
b101000 *
1'
#420000
0'
#425000
b101001 *
1'
#430000
0'
#435000
b101010 *
1'
#440000
0'
#445000
b1 0
1)
b101011 *
1'
#450000
0'
#455000
0)
b101100 *
b1 /
1'
#460000
0'
#465000
b101101 *
1'
#470000
0'
#475000
b101110 *
1'
#480000
0'
#485000
b101111 *
1'
#490000
0'
#495000
b110000 *
1'
#500000
0'
#505000
b10 0
1)
b110001 *
1'
#510000
0'
#515000
0)
b110010 *
b10 /
1'
#520000
0'
#525000
b110011 *
1'
#530000
0'
#535000
b110100 *
1'
#540000
0'
#545000
b110101 *
1'
#550000
0'
#555000
b110110 *
1'
#560000
0'
#565000
b11 0
1)
b110111 *
1'
#570000
0'
#575000
0)
b111000 *
b11 /
1'
#580000
0'
#585000
b111001 *
1'
#590000
0'
#595000
b111010 *
1'
#600000
0'
#605000
b111011 *
1'
#610000
0'
#615000
b111100 *
1'
#620000
0'
#625000
b100 0
1)
b111101 *
1'
#630000
0'
#635000
0)
b111110 *
b100 /
1'
#640000
0'
#645000
b111111 *
1'
#650000
0'
#655000
b1000000 *
1'
#660000
0'
#665000
b1000001 *
1'
#670000
0'
#675000
b1000010 *
1'
#680000
0'
#685000
b0 0
b11 2
1)
b1000011 *
1'
#690000
0'
#695000
1$
0&
1"
0)
b1000100 *
b0 /
b11 1
1'
#700000
0'
#705000
b1000101 *
1'
#710000
0'
#715000
b1000110 *
1'
#720000
0'
#725000
b1000111 *
1'
#730000
0'
#735000
b1001000 *
1'
#740000
0'
#745000
b1 0
1)
b1001001 *
1'
#750000
0'
#755000
0)
b1001010 *
b1 /
1'
#760000
0'
#765000
b1001011 *
1'
#770000
0'
#775000
b1001100 *
1'
#780000
0'
#785000
b1001101 *
1'
#790000
0'
#795000
b1001110 *
1'
#800000
0'
#805000
b0 0
b0 2
1)
b1001111 *
1'
#810000
0'
#815000
1%
1#
0$
0"
0)
b1010000 *
b0 /
b0 1
1'
#820000
0'
#825000
b1010001 *
1'
#830000
0'
#835000
b1010010 *
1'
#840000
0'
#845000
b1010011 *
1'
#850000
0'
#855000
b1010100 *
1'
#860000
0'
#865000
b1 0
1)
b1010101 *
1'
#870000
0'
#875000
0)
b1010110 *
b1 /
1'
#880000
0'
#885000
b1010111 *
1'
#890000
0'
#895000
b1011000 *
1'
#900000
0'
#905000
b1011001 *
1'
#910000
0'
#915000
b1011010 *
1'
#920000
0'
#925000
b10 0
1)
b1011011 *
1'
#930000
0'
#935000
0)
b1011100 *
b10 /
1'
#940000
0'
#945000
b1011101 *
1'
#950000
0'
#955000
b1011110 *
1'
#960000
0'
#965000
b1011111 *
1'
#970000
0'
#975000
b1100000 *
1'
#980000
0'
#985000
b11 0
1)
b1100001 *
1'
#990000
0'
#995000
0)
b1100010 *
b11 /
1'
#1000000
0'
#1005000
b1100011 *
1'
#1010000
0'
#1015000
b1100100 *
1'
#1020000
0'
#1025000
b1100101 *
1'
#1030000
0'
#1035000
b1100110 *
1'
#1040000
0'
#1045000
b100 0
1)
b1100111 *
1'
#1050000
0'
#1055000
0)
b1101000 *
b100 /
1'
#1060000
0'
#1065000
b1101001 *
1'
#1070000
0'
#1075000
b1101010 *
1'
#1080000
0'
#1085000
b1101011 *
1'
#1090000
0'
#1095000
b1101100 *
1'
#1100000
0'
#1105000
b0 0
b1 2
1)
b1101101 *
1'
#1110000
0'
#1115000
1!
1%
0#
0)
b1101110 *
b0 /
b1 1
1'
#1120000
0'
#1125000
b1101111 *
1'
#1130000
0'
#1135000
b1110000 *
1'
#1140000
0'
#1145000
b1110001 *
1'
#1150000
0'
#1155000
b1110010 *
1'
#1160000
0'
#1165000
b1 0
1)
b1110011 *
1'
#1170000
0'
#1175000
0)
b1110100 *
b1 /
1'
#1180000
0'
#1185000
b1110101 *
1'
#1190000
0'
#1195000
b1110110 *
1'
#1200000
0'
#1205000
b1110111 *
1'
#1210000
0'
#1215000
b1111000 *
1'
#1220000
0'
#1225000
b0 0
b10 2
1)
b1111001 *
1'
#1230000
0'
#1235000
1"
1&
0%
0!
0)
b1111010 *
b0 /
b10 1
1'
#1240000
0'
#1245000
b1111011 *
1'
#1250000
0'
#1255000
b1111100 *
1'
#1260000
0'
#1265000
b1111101 *
1'
#1270000
0'
#1275000
b1111110 *
1'
#1280000
0'
#1285000
b1 0
1)
b1111111 *
1'
#1290000
0'
#1295000
0)
b10000000 *
b1 /
1'
#1300000
0'
#1305000
b10000001 *
1'
#1310000
0'
#1315000
b10000010 *
1'
#1320000
0'
#1325000
b10000011 *
1'
#1330000
0'
#1335000
b10000100 *
1'
#1340000
0'
#1345000
b10 0
1)
b10000101 *
1'
#1350000
0'
#1355000
0)
b10000110 *
b10 /
1'
#1360000
0'
#1365000
b10000111 *
1'
#1370000
0'
#1375000
b10001000 *
1'
#1380000
0'
#1385000
b10001001 *
1'
#1390000
0'
#1395000
b10001010 *
1'
#1400000
0'
#1405000
b11 0
1)
b10001011 *
1'
#1410000
0'
#1415000
0)
b10001100 *
b11 /
1'
#1420000
0'
#1425000
b10001101 *
1'
#1430000
0'
#1435000
b10001110 *
1'
#1440000
0'
#1445000
b10001111 *
1'
#1450000
0'
#1455000
b10010000 *
1'
#1460000
0'
#1465000
b100 0
1)
b10010001 *
1'
#1470000
0'
#1475000
0)
b10010010 *
b100 /
1'
#1480000
0'
#1485000
b10010011 *
1'
#1490000
0'
#1495000
b10010100 *
1'
#1500000
0'
#1505000
b10010101 *
1'
#1510000
0'
#1515000
b10010110 *
1'
#1520000
0'
#1525000
b0 0
b11 2
1)
b10010111 *
1'
#1530000
0'
#1535000
1$
0&
1"
0)
b10011000 *
b0 /
b11 1
1'
#1540000
0'
#1545000
b10011001 *
1'
#1550000
0'
#1555000
b10011010 *
1'
#1560000
0'
#1565000
b10011011 *
1'
#1570000
0'
#1575000
b10011100 *
1'
#1580000
0'
#1585000
b1 0
1)
b10011101 *
1'
#1590000
0'
#1595000
0)
b10011110 *
b1 /
1'
#1600000
0'
#1605000
b10011111 *
1'
#1610000
0'
#1615000
b10100000 *
1'
#1620000
0'
#1625000
b10100001 *
1'
#1630000
0'
#1635000
b10100010 *
1'
#1640000
0'
#1645000
b0 0
b0 2
1)
b10100011 *
1'
#1650000
0'
#1655000
1%
1#
0$
0"
0)
b10100100 *
b0 /
b0 1
1'
#1660000
0'
#1665000
b10100101 *
1'
#1670000
0'
#1675000
b10100110 *
1'
#1680000
0'
#1685000
b10100111 *
1'
#1690000
0'
#1695000
b10101000 *
1'
#1700000
0'
#1705000
b1 0
1)
b10101001 *
1'
#1710000
0'
#1715000
0)
b10101010 *
b1 /
1'
#1720000
0'
#1725000
b10101011 *
1'
#1730000
0'
#1735000
b10101100 *
1'
#1740000
0'
#1745000
b10101101 *
1'
#1750000
0'
#1755000
b10101110 *
1'
#1760000
0'
#1765000
b10 0
1)
b10101111 *
1'
#1770000
0'
#1775000
0)
b10110000 *
b10 /
1'
#1780000
0'
#1785000
b10110001 *
1'
#1790000
0'
#1795000
b10110010 *
1'
#1800000
0'
#1805000
b10110011 *
1'
#1810000
0'
#1815000
b10110100 *
1'
#1820000
0'
#1825000
b11 0
1)
b10110101 *
1'
#1830000
0'
#1835000
0)
b10110110 *
b11 /
1'
#1840000
0'
#1845000
b10110111 *
1'
#1850000
0'
#1855000
b10111000 *
1'
#1860000
0'
#1865000
b10111001 *
1'
#1870000
0'
#1875000
b10111010 *
1'
#1880000
0'
#1885000
b100 0
1)
b10111011 *
1'
#1890000
0'
#1895000
0)
b10111100 *
b100 /
1'
#1900000
0'
#1905000
b10111101 *
1'
#1910000
0'
#1915000
b10111110 *
1'
#1920000
0'
#1925000
b10111111 *
1'
#1930000
0'
#1935000
b11000000 *
1'
#1940000
0'
#1945000
b0 0
b1 2
1)
b11000001 *
1'
#1950000
0'
#1955000
1!
1%
0#
0)
b11000010 *
b0 /
b1 1
1'
#1960000
0'
#1965000
b11000011 *
1'
#1970000
0'
#1975000
b11000100 *
1'
#1980000
0'
#1985000
b11000101 *
1'
#1990000
0'
#1995000
b11000110 *
1'
#2000000
0'
#2005000
b1 0
1)
b11000111 *
1'
#2010000
0'
#2015000
0)
b11001000 *
b1 /
1'
#2020000
0'
#2025000
b11001001 *
1'
#2030000
0'
#2035000
b11001010 *
1'
#2040000
0'
#2045000
b11001011 *
1'
#2050000
0'
#2055000
b11001100 *
1'
#2060000
0'
#2065000
b0 0
b10 2
1)
b11001101 *
1'
#2070000
0'
#2075000
1"
1&
0%
0!
0)
b11001110 *
b0 /
b10 1
1'
#2080000
0'
#2085000
b11001111 *
1'
#2090000
0'
#2095000
b11010000 *
1'
#2100000
0'
#2105000
b11010001 *
1'
#2110000
0'
#2115000
b11010010 *
1'
#2120000
0'
#2125000
b1 0
1)
b11010011 *
1'
#2130000
0'
#2135000
0)
b11010100 *
b1 /
1'
#2140000
0'
#2145000
b11010101 *
1'
#2150000
0'
#2155000
b11010110 *
1'
#2160000
0'
#2165000
b11010111 *
1'
#2170000
0'
#2175000
b11011000 *
1'
#2180000
0'
#2185000
b10 0
1)
b11011001 *
1'
#2190000
0'
#2195000
0)
b11011010 *
b10 /
1'
#2200000
0'
#2205000
b11011011 *
1'
#2210000
0'
#2215000
b11011100 *
1'
#2220000
0'
#2225000
b11011101 *
1'
#2230000
0'
#2235000
b11011110 *
1'
#2240000
0'
#2245000
b11 0
1)
b11011111 *
1'
#2250000
0'
#2255000
0)
b11100000 *
b11 /
1'
#2260000
0'
#2265000
b11100001 *
1'
#2270000
0'
#2275000
b11100010 *
1'
#2280000
0'
#2285000
b11100011 *
1'
#2290000
0'
#2295000
b11100100 *
1'
#2300000
0'
#2305000
b100 0
1)
b11100101 *
1'
#2310000
0'
#2315000
0)
b11100110 *
b100 /
1'
#2320000
0'
#2325000
b11100111 *
1'
#2330000
0'
#2335000
b11101000 *
1'
#2340000
0'
#2345000
b11101001 *
1'
#2350000
0'
#2355000
b11101010 *
1'
#2360000
0'
#2365000
b0 0
b11 2
1)
b11101011 *
1'
#2370000
0'
#2375000
1$
0&
1"
0)
b11101100 *
b0 /
b11 1
1'
#2380000
0'
#2385000
b11101101 *
1'
#2390000
0'
#2395000
b11101110 *
1'
#2400000
0'
#2405000
b11101111 *
1'
#2410000
0'
#2415000
b11110000 *
1'
#2420000
0'
#2425000
b1 0
1)
b11110001 *
1'
#2430000
0'
#2435000
0)
b11110010 *
b1 /
1'
#2440000
0'
#2445000
b11110011 *
1'
#2450000
0'
#2455000
b11110100 *
1'
#2460000
0'
#2465000
b11110101 *
1'
#2470000
0'
#2475000
b11110110 *
1'
#2480000
0'
#2485000
b0 0
b0 2
1)
b11110111 *
1'
#2490000
0'
#2495000
1%
1#
0$
0"
0)
b11111000 *
b0 /
b0 1
1'
#2500000
0'
#2505000
b11111001 *
1'
#2510000
0'
#2515000
b11111010 *
1'
#2520000
0'
#2525000
b11111011 *
1'
