FSM Assignment/P1_seqdet/seq_detector_mealy.v
`timescale 1ns / 1ps
//////////////////////////////////////////////////////////////////////////////////
// Sequence Detector (Mealy FSM)
// Pattern: 1101 (with overlap)
// Verilog-2005 compatible (no typedef/enum)
//////////////////////////////////////////////////////////////////////////////////

module seq_detector_mealy(
    input  wire clk,
    input  wire rst_n,   // active-low reset
    input  wire din,
    output wire dout
);

    // state encoding using parameters
    parameter S0 = 2'b00;  // no match
    parameter S1 = 2'b01;  // seen '1'
    parameter S2 = 2'b10;  // seen "11"
    parameter S3 = 2'b11;  // seen "110"

    reg [1:0] cur_state, nxt_state;

    // state register
    always @(posedge clk) begin
        if (!rst_n) 
            cur_state <= S0;
        else        
            cur_state <= nxt_state;
    end

    // next state logic
    always @(*) begin
        case (cur_state)
            S0:   nxt_state = (din) ? S1 : S0;
            S1:   nxt_state = (din) ? S2 : S0;
            S2:   nxt_state = (din) ? S2 : S3;
            S3:   nxt_state = (din) ? S1 : S0;
            default: nxt_state = S0;
        endcase
    end

    // output logic (Mealy)
    assign dout = (cur_state == S3) & din;

endmodule

FSM Assignment/P1_seqdet/tb_seq_detector_mealy.v
`timescale 1ns / 1ps
//////////////////////////////////////////////////////////////////////////////////
// Testbench: Sequence Detector (Mealy FSM)
// Pattern: 1101 with overlap
//////////////////////////////////////////////////////////////////////////////////

module tb_seq_detector_mealy;

    reg clk_tb;
    reg rst_n_tb;
    reg din_tb;
    wire dout_tb;

    // DUT instance
    seq_detector_mealy uut (
        .clk  (clk_tb),
        .rst_n(rst_n_tb),
        .din  (din_tb),
        .dout (dout_tb)
    );

    // Clock generation (20ns period, i.e. 50 MHz)
    initial clk_tb = 0;
    always #10 clk_tb = ~clk_tb;

    // Stimulus
    initial begin
        // VCD dump for GTKWave
        $dumpfile("tb_seq_detector_mealy.vcd");
        $dumpvars(0, tb_seq_detector_mealy);

        // Apply reset (active-low)
        rst_n_tb = 0;
        din_tb   = 0;
        repeat(2) @(posedge clk_tb);
        rst_n_tb = 1;

        // --- Sequence #1: 1101 (expect one detection) ---
        drive_bits(4, 4'b1101);

        // --- Sequence #2: 1101101 (expect overlap detections) ---
        drive_bits(7, 7'b1101101);

        // --- Sequence #3: 01101101 (expect multiple hits) ---
        drive_bits(8, 8'b01101101);

        // --- Sequence #4: 111101 (expect pulse near end) ---
        drive_bits(6, 6'b111101);

        // End simulation
        #50;
        $display("\n[TB] Testbench completed.\n");
        $finish;
    end

    // Task to feed a sequence bit-by-bit (Verilog-2005 friendly)
    task drive_bits;
        input integer n;        // number of bits
        input [31:0] seq;       // sequence (max 32 bits)
        integer i;
        begin
            for (i = n-1; i >= 0; i = i-1) begin
                din_tb = seq[i];
                @(posedge clk_tb);
            end
        end
    endtask

endmodule

FSM Assignment/P1_seqdet/tb_seq_detector_mealy.vcd
$date
	Mon Sep 01 22:52:58 2025
$end
$version
	Icarus Verilog
$end
$timescale
	1ps
$end
$scope module tb_seq_detector_mealy $end
$var wire 1 ! dout_tb $end
$var reg 1 " clk_tb $end
$var reg 1 # din_tb $end
$var reg 1 $ rst_n_tb $end
$scope module uut $end
$var wire 1 " clk $end
$var wire 1 # din $end
$var wire 1 ! dout $end
$var wire 1 $ rst_n $end
$var parameter 2 % S0 $end
$var parameter 2 & S1 $end
$var parameter 2 ' S2 $end
$var parameter 2 ( S3 $end
$var reg 2 ) cur_state [1:0] $end
$var reg 2 * nxt_state [1:0] $end
$upscope $end
$scope task drive_bits $end
$var reg 32 + seq [31:0] $end
$var integer 32 , i [31:0] $end
$var integer 32 - n [31:0] $end
$upscope $end
$upscope $end
$enddefinitions $end
$comment Show the parameter values. $end
$dumpall
b11 (
b10 '
b1 &
b0 %
$end
#0
$dumpvars
bx -
bx ,
bx +
b0 *
bx )
0$
0#
0"
0!
$end
#10000
b0 )
1"
#20000
0"
#30000
b1 *
1#
b11 ,
b1101 +
b100 -
1$
1"
#40000
0"
#50000
b10 *
b1 )
b10 ,
1"
#60000
0"
#70000
b10 )
b11 *
0#
b1 ,
1"
#80000
0"
#90000
1!
b11 )
b1 *
1#
b0 ,
1"
#100000
0"
#110000
b10 *
0!
b1 )
b1101101 +
b111 -
b110 ,
1"
#120000
0"
#130000
b10 )
b101 ,
1"
#140000
0"
#150000
b11 *
0#
b100 ,
1"
#160000
0"
#170000
1!
b11 )
b1 *
1#
b11 ,
1"
#180000
0"
#190000
b10 *
0!
b1 )
b10 ,
1"
#200000
0"
#210000
b10 )
b11 *
0#
b1 ,
1"
#220000
0"
#230000
1!
b11 )
b1 *
1#
b0 ,
1"
#240000
0"
#250000
b1 )
0!
b0 *
0#
b1000 -
b111 ,
1"
#260000
0"
#270000
b0 )
b1 *
1#
b110 ,
1"
#280000
0"
#290000
b10 *
b1 )
b101 ,
1"
#300000
0"
#310000
b10 )
b11 *
0#
b100 ,
1"
#320000
0"
#330000
1!
b11 )
b1 *
1#
b11 ,
1"
#340000
0"
#350000
b10 *
0!
b1 )
b10 ,
1"
#360000
0"
#370000
b10 )
b11 *
0#
b1 ,
1"
#380000
0"
#390000
1!
b11 )
b1 *
1#
b0 ,
1"
#400000
0"
#410000
b10 *
0!
b1 )
b111101 +
b110 -
b101 ,
1"
#420000
0"
#430000
b10 )
b100 ,
1"
#440000
0"
#450000
b11 ,
1"
#460000
0"
#470000
b10 ,
1"
#480000
0"
#490000
b11 *
0#
b1 ,
1"
#500000
0"
#510000
1!
b11 )
b1 *
1#
b0 ,
1"
#520000
0"
#530000
b10 *
0!
b1 )
b11111111111111111111111111111111 ,
1"
#540000
0"
#550000
b10 )
1"
